README.rst
setup.py
bin/dir2yaml
bin/yaml2dir
pyvert/__init__.py
pyvert/convert_dict.py
pyvert/convert_dir.py
pyvert.egg-info/PKG-INFO
pyvert.egg-info/SOURCES.txt
pyvert.egg-info/dependency_links.txt
pyvert.egg-info/not-zip-safe
pyvert.egg-info/requires.txt
pyvert.egg-info/top_level.txt