Metadata-Version: 1.1
Name: pyvert
Version: 0.4
Summary: pyvert is a tool to convert a filesystem directory structure to and from YAML
Home-page: http://github.com/blaketmiller/pyvert
Author: Blake Miller
Author-email: blakethomasmiller@gmail.com
License: GNU GPL v2.0
Keywords: convert folder file dictionary yaml structure filesystem represent utility
Platform: UNKNOWN
Classifier: Intended Audience :: Developers
Classifier: Intended Audience :: Information Technology
Classifier: License :: OSI Approved :: GNU General Public License v2 (GPLv2)
Classifier: Natural Language :: English
Classifier: Operating System :: POSIX :: Linux
Classifier: Programming Language :: Python :: 2.7
Classifier: Topic :: Software Development :: Testing
Classifier: Topic :: Software Development :: Libraries :: Python Modules
Classifier: Topic :: System :: Filesystems
Classifier: Topic :: System :: Archiving
Classifier: Topic :: Utilities
